up_counter_4bit/up_counter_4bit.v
module up_counter_4bit(
	input clk,
	input reset,
	output reg [3:0]count);

	always @(posedge clk or posedge reset)
		
		begin
			if(reset)
				count <= 4'b0000;
			else
				count <= count+1;
		end
endmodule

up_counter_4bit/up_counter_tb.v
module up_counter_tb;
	reg clk;
	reg reset;
	wire [3:0]count;

up_counter_4bit uut(
	.clk(clk),
	.reset(reset),
	.count(count)
);

initial begin
	clk=0;
	forever #1 clk = ~clk;
end

initial begin
	$dumpfile("up_counter_4bit.vcd");
	$dumpvars();

	reset = 1;
	repeat(2) @(negedge clk);

	reset = 0;
	
	repeat(20) @(negedge clk);
	$finish;
end
always @(posedge clk)begin
	$strobe("Time = %t | Reset = %b | Count = %b |",$time,reset,count);
end
endmodule

up_counter_4bit/obj_dir/up_counter_4bit.vcd
$version Generated by VerilatedVcd $end
$timescale 1ps $end
 $scope module up_counter_tb $end
  $var wire 1 # clk $end
  $var wire 1 $ reset $end
  $var wire 4 % count [3:0] $end
  $scope module uut $end
   $var wire 1 # clk $end
   $var wire 1 $ reset $end
   $var wire 4 % count [3:0] $end
  $upscope $end
 $upscope $end
$enddefinitions $end


#0
0#
1$
b0000 %
#1
1#
#2
0#
#3
1#
#4
0#
0$
#5
1#
b0001 %
#6
0#
#7
1#
b0010 %
#8
0#
#9
1#
b0011 %
#10
0#
#11
1#
b0100 %
#12
0#
#13
1#
b0101 %
#14
0#
#15
1#
b0110 %
#16
0#
#17
1#
b0111 %
#18
0#
#19
1#
b1000 %
#20
0#
#21
1#
b1001 %
#22
0#
#23
1#
b1010 %
#24
0#
#25
1#
b1011 %
#26
0#
#27
1#
b1100 %
#28
0#
#29
1#
b1101 %
#30
0#
#31
1#
b1110 %
#32
0#
#33
1#
b1111 %
#34
0#
#35
1#
b0000 %
#36
0#
#37
1#
b0001 %
#38
0#
#39
1#
b0010 %
#40
0#
#41
1#
b0011 %
#42
0#
#43
1#
b0100 %
