jk_flipflop/jk_ff.v
module jk_ff(
	input j,
	input k,
	input reset,
	input clk,
	output reg q,
	output qn
);

assign qn = ~q;

always@ (posedge clk)begin
	if (reset)
		q <= 1'b0;
	else
		case({j,k})
			2'b00: q <= q;
			2'b01: q<= 1'b0;
			2'b10: q<= 1'b1;
			2'b11: q<= ~q;
		endcase
	end
	endmodule

jk_flipflop/jk_ff_tb.v
module jk_ff_tb;
reg reset,clk;
reg j,k;
wire q,qn;

jk_ff uut(
	.j(j),.k(k),.clk(clk),.reset(reset),
	.q(q),.qn(qn)
);

always #5 clk = ~clk;
initial begin
	$monitor($time, "\t Reset = %0b j=%0b k=%0b q=%0b qn=%0b", reset, j, k, q, qn);
end;
initial begin
	clk = 1'b0;
	reset = 1'b1;
	#10 reset = 1'b0;
	#10 j = 1'b0; k = 1'b0;
	#10 j = 1'b0; k = 1'b1;
	#10 j = 1'b1; k = 1'b0;
	#10 j = 1'b1; k = 1'b1;
	#10 j = 1'b1; k = 1'b1;
	#10 j = 1'b0; k = 1'b0;
	#20;
	$finish;
end
initial begin
	$dumpfile("jk_ff.vcd");
	$dumpvars();
end
endmodule

jk_flipflop/obj_dir/jk_ff.vcd
$version Generated by VerilatedVcd $end
$timescale 1ps $end
 $scope module jk_ff_tb $end
  $var wire 1 # reset $end
  $var wire 1 $ clk $end
  $var wire 1 % j $end
  $var wire 1 & k $end
  $var wire 1 ' q $end
  $var wire 1 ( qn $end
  $scope module uut $end
   $var wire 1 % j $end
   $var wire 1 & k $end
   $var wire 1 # reset $end
   $var wire 1 $ clk $end
   $var wire 1 ' q $end
   $var wire 1 ( qn $end
  $upscope $end
 $upscope $end
$enddefinitions $end


#0
1#
0$
0%
0&
0'
1(
#5
1$
#10
0#
0$
#15
1$
#20
0$
#25
1$
#30
0$
1&
#35
1$
#40
0$
1%
0&
#45
1$
1'
0(
#50
0$
1&
#55
1$
0'
1(
#60
0$
#65
1$
1'
0(
#70
0$
0%
0&
