simple_reset_demo/counter_sync.v
module counter_sync (
    input  wire clk,
    input  wire rst_sync,
    output reg [3:0] count
);
    always @(posedge clk) begin
        if (rst_sync)
            count <= 4'd0;
        else
            count <= count + 1;
    end
endmodule

simple_reset_demo/reset_sync.v
module reset_sync (
    input  wire clk,
    input  wire rst_async,
    output reg  rst_sync
);
    reg stage1;

    always @(posedge clk or posedge rst_async) begin
        if (rst_async) begin
            stage1   <= 1'b1;
            rst_sync <= 1'b1;
        end else begin
            stage1   <= 1'b0;
            rst_sync <= stage1;
        end
    end
endmodule

simple_reset_demo/counter_async.v
module counter_async (
    input  wire clk,
    input  wire rst,       // async reset
    output reg [3:0] count
);
    always @(posedge clk or posedge rst) begin
        if (rst)
            count <= 4'd0;
        else
            count <= count + 1; end
endmodule

simple_reset_demo/tb.v
module tb;

    reg clk = 0;
    reg rst = 0;

    wire [3:0] cnt_async;
    wire [3:0] cnt_sync;
    wire rst_sync;

   // Clock
    always #5 clk = ~clk;

    // DUTs
    counter_async u_async (.clk(clk), .rst(rst), .count(cnt_async));
    reset_sync    u_sync  (.clk(clk), .rst_async(rst), .rst_sync(rst_sync));
    counter_sync  u_syncc (.clk(clk), .rst_sync(rst_sync), .count(cnt_sync));

    initial begin
        $dumpfile("dump.vcd");
        $dumpvars(0, tb);

        // Step 1: Assert reset
        rst = 1;
        #25;

        // Step 2: Deassert reset (possibly in middle of a clock cycle)
        rst = 0;
        #100;

        // Step 3: Assert/deassert reset again
        rst = 1;
        #20;
        rst = 0;

        #50;
        $finish;
    end
endmodule

simple_reset_demo/obj_dir/dump.vcd
$version Generated by VerilatedVcd $end
$timescale 1ps $end
 $scope module tb $end
  $var wire 1 # clk $end
  $var wire 1 $ rst $end
  $var wire 4 % cnt_async [3:0] $end
  $var wire 4 & cnt_sync [3:0] $end
  $var wire 1 ' rst_sync $end
  $scope module u_async $end
   $var wire 1 # clk $end
   $var wire 1 $ rst $end
   $var wire 4 % count [3:0] $end
  $upscope $end
  $scope module u_sync $end
   $var wire 1 # clk $end
   $var wire 1 $ rst_async $end
   $var wire 1 ' rst_sync $end
   $var wire 1 ( stage1 $end
  $upscope $end
  $scope module u_syncc $end
   $var wire 1 # clk $end
   $var wire 1 ' rst_sync $end
   $var wire 4 & count [3:0] $end
  $upscope $end
 $upscope $end
$enddefinitions $end


#0
0#
1$
b0000 %
b0000 &
1'
1(
#5
1#
#10
0#
#15
1#
#20
0#
#25
1#
0$
b0001 %
0(
#30
0#
#35
1#
b0010 %
0'
#40
0#
#45
1#
b0011 %
b0001 &
#50
0#
#55
1#
b0100 %
b0010 &
#60
0#
#65
1#
b0101 %
b0011 &
#70
0#
#75
1#
b0110 %
b0100 &
#80
0#
#85
1#
b0111 %
b0101 &
#90
0#
#95
1#
b1000 %
b0110 &
#100
0#
#105
1#
b1001 %
b0111 &
#110
0#
#115
1#
b1010 %
b1000 &
#120
0#
#125
1#
1$
b0000 %
b1001 &
1'
1(
#130
0#
#135
1#
b0000 &
#140
0#
#145
1#
0$
b0001 %
0(
#150
0#
#155
1#
b0010 %
0'
#160
0#
#165
1#
b0011 %
b0001 &
#170
0#
#175
1#
b0100 %
b0010 &
#180
0#
#185
1#
b0101 %
b0011 &
#190
0#
#195
1#
b0110 %
b0100 &
